README.rst
setup.py
chatter_client.egg-info/PKG-INFO
chatter_client.egg-info/SOURCES.txt
chatter_client.egg-info/dependency_links.txt
chatter_client.egg-info/not-zip-safe
chatter_client.egg-info/top_level.txt
foo/__init__.py